ninesix/__init__.py
ninesix/log.py
ninesix/util.py
ninesix/tool/__init__.py
ninesix/tool/grid.py
ninesix/writer/__init__.py
ninesix/writer/json_writer.py
ninesix/writer/stdout_writer.py
ninesix-0.0.4.dist-info/LICENSE
ninesix-0.0.4.dist-info/METADATA
ninesix-0.0.4.dist-info/WHEEL
ninesix-0.0.4.dist-info/entry_points.txt
ninesix-0.0.4.dist-info/top_level.txt
ninesix-0.0.4.dist-info/RECORD
