Metadata-Version: 2.1
Name: ninesix
Version: 0.0.4
Summary: Easy-to-use unified tools for NN logging and managing.
Home-page: https://github.com/JogleLew/nine-six
Author: Jogle Lew
Author-email: author@example.com
License: AGPLv3+
Keywords: Nine Six,nine-six,Logging,Logger,Grid Search
Platform: UNKNOWN
Classifier: Development Status :: 4 - Beta
Classifier: License :: OSI Approved :: GNU Affero General Public License v3 or later (AGPLv3+)
Classifier: Intended Audience :: Developers
Classifier: Intended Audience :: End Users/Desktop
Classifier: Programming Language :: Python :: 3 :: Only
Classifier: Topic :: Software Development :: Libraries :: Application Frameworks
Classifier: Topic :: Utilities
Requires-Python: >=3.0
Requires-Dist: more-itertools
